geecracker/__init__.py
geecracker/geecracker.py
geecracker-0.0.2.dist-info/LICENSE
geecracker-0.0.2.dist-info/METADATA
geecracker-0.0.2.dist-info/WHEEL
geecracker-0.0.2.dist-info/top_level.txt
geecracker-0.0.2.dist-info/RECORD
