Metadata-Version: 2.1
Name: geecracker
Version: 0.0.2
Summary: A cracker of geetest depends on selenium
Home-page: https://github.com/xiaminghu/GeetestCracker
Author: hugo
Maintainer: hugo
Maintainer-email: minghuhugo@163.com
License: MIT
Project-URL: Documentation, https://github.com/xiaminghu/GeetestCracker
Project-URL: Source, https://github.com/xiaminghu/GeetestCracker
Project-URL: Tracker, https://github.com/xiaminghu/GeetestCracker/issues
Platform: UNKNOWN
Classifier: Programming Language :: Python :: 3
Classifier: License :: OSI Approved :: MIT License
Classifier: Operating System :: OS Independent
Requires-Python: >=3.6
Requires-Dist: selenium
Requires-Dist: pillow
